jcore/__init__.py
jcore/__main__.py
jcore/client.py
jcore/exceptions.py
jcore/jsocket.py
jcore/message.py
jcore/messageparser.py
jcore/extensions/__init__.py
jcore/extensions/module.py
jcore/helpers/__init__.py
jcore/helpers/settings.py
jcore/modules/__init__.py
jcore/modules/creator.py
jcore/modules/ping.py
jcore-0.2.0.552.dist-info/LICENSE
jcore-0.2.0.552.dist-info/METADATA
jcore-0.2.0.552.dist-info/WHEEL
jcore-0.2.0.552.dist-info/top_level.txt
jcore-0.2.0.552.dist-info/RECORD
