Metadata-Version: 2.1
Name: jcore
Version: 0.2.0.552
Summary: A python package for creating Twitch Bots
Home-page: https://github.com/cubbei/jcore
Author: Cubbei
Author-email: cubbei@outlook.com
License: GPL
Platform: UNKNOWN
Classifier: Programming Language :: Python :: 3
Classifier: Programming Language :: Python :: 3.7
Classifier: Programming Language :: Python :: 3.8
Classifier: Programming Language :: Python :: 3.9
Classifier: License :: OSI Approved :: GNU General Public License v3 or later (GPLv3+)
Classifier: Operating System :: OS Independent
Requires-Python: >=3.7
License-File: LICENSE
Requires-Dist: asyncio
Requires-Dist: pyyaml
